medpcpy.py
medpcpy-0.1.3.dist-info/LICENSE
medpcpy-0.1.3.dist-info/WHEEL
medpcpy-0.1.3.dist-info/METADATA
medpcpy-0.1.3.dist-info/RECORD
