Metadata-Version: 2.1
Name: medpcpy
Version: 0.1.3
Summary: A library to facilitate the analysis of behavioral data generated by Med equipment
Home-page: https://github.com/JuodaanViinaa/MedPCPy/
License: GPL-3.0-or-later
Author: Daniel Maldonado
Author-email: maldonadodaniel96@outlook.com
Requires-Python: >=3.7,<4.0
Classifier: License :: OSI Approved :: GNU General Public License v3 or later (GPLv3+)
Classifier: Programming Language :: Python :: 3
Classifier: Programming Language :: Python :: 3.7
Classifier: Programming Language :: Python :: 3.8
Classifier: Programming Language :: Python :: 3.9
Classifier: Programming Language :: Python :: 3.10
Classifier: Programming Language :: Python :: 3.11
Requires-Dist: openpyxl (>=3.0.10,<4.0.0)
Requires-Dist: pandas (>=1.4.2,<2.0.0)
